tastypie_user_session
