Metadata-Version: 1.1
Name: tastypie-user-session
Version: 0.3
Summary: User sessions on top of Tastypie, plus Facebook auth
Home-page: https://github.com/tudorprodan/tastypie_user_session/
Author: Tudor Prodan
Author-email: tudor.prodan@gmail.com
License: MIT
Keywords: tastypie session authentication facebook
Platform: UNKNOWN
Requires: django_tastypie
Requires: django
